graphs_emelend4/__init__.py
graphs_emelend4/heapq.py
graphs_emelend4/sp.py
graphs_emelend4-0.0.1.dist-info/METADATA
graphs_emelend4-0.0.1.dist-info/WHEEL
graphs_emelend4-0.0.1.dist-info/RECORD
