Metadata-Version: 2.3
Name: graphs_emelend4
Version: 0.0.1
Summary: Dijkstra's shortest path algorithm and other paths
Author-email: Emily Melendez <emelend4@msudenver.edu>
Classifier: License :: OSI Approved :: MIT License
Classifier: Operating System :: OS Independent
Classifier: Programming Language :: Python :: 3
Requires-Python: >=3.7
